sng_tk/__init__.py
sng_tk/config.py
sng_tk/general.py
sng_tk/log.py
sng_tk/mqtt_client.py
sng_tk/tools.py
sng_tk-1.2.3.dist-info/LICENSE
sng_tk-1.2.3.dist-info/METADATA
sng_tk-1.2.3.dist-info/WHEEL
sng_tk-1.2.3.dist-info/top_level.txt
sng_tk-1.2.3.dist-info/RECORD
