Metadata-Version: 2.1
Name: sng-tk
Version: 1.2.3
Summary: SNG development Tools Kit
Home-page: http://gitlab.digital-work.cn/sng_cloud
Author: Maicss
Author-email: fengchen.liu@sng.com.cn
Classifier: Development Status :: 1 - Planning
Classifier: Programming Language :: Python :: 3
Classifier: License :: OSI Approved :: MIT License
License-File: LICENSE
Requires-Dist: colorlog
Requires-Dist: paho-mqtt
